princeton_scraper_seas_faculty/__init__.py
princeton_scraper_seas_faculty/__main__.py
princeton_scraper_seas_faculty/campus_directory.py
princeton_scraper_seas_faculty/constants.py
princeton_scraper_seas_faculty/helpers.py
princeton_scraper_seas_faculty/output.py
princeton_scraper_seas_faculty/seas_faculty_directory.py
princeton_scraper_seas_faculty-1.3.0.dist-info/LICENSE
princeton_scraper_seas_faculty-1.3.0.dist-info/WHEEL
princeton_scraper_seas_faculty-1.3.0.dist-info/METADATA
princeton_scraper_seas_faculty-1.3.0.dist-info/RECORD
