Metadata-Version: 2.1
Name: princeton-scraper-seas-faculty
Version: 1.3.0
Summary: A web scraper that produces JSON feeds directly and automatically from the Princeton SEAS faculty directory.
Author: Jérémie Lumbroso
Author-email: lumbroso@cs.princeton.edu
Requires-Python: >=3.8,<4.0
Classifier: Programming Language :: Python :: 3
Classifier: Programming Language :: Python :: 3.10
Classifier: Programming Language :: Python :: 3.8
Classifier: Programming Language :: Python :: 3.9
Requires-Dist: bs4 (>=0.0.1,<0.0.2)
Requires-Dist: comma (==0.5.3)
Requires-Dist: requests (>=2.24.0,<3.0.0)
